LICENSE
MANIFEST.in
README.rst
setup.py
OpenRAI.egg-info/PKG-INFO
OpenRAI.egg-info/SOURCES.txt
OpenRAI.egg-info/dependency_links.txt
OpenRAI.egg-info/requires.txt
OpenRAI.egg-info/top_level.txt
RAI/__init__.py
RAI/all_types.py
RAI/AISystem/__init__.py
RAI/AISystem/ai_system.py
RAI/AISystem/model.py
RAI/Analysis/__init__.py
RAI/Analysis/analysis.py
RAI/Analysis/analysis_manager.py
RAI/Analysis/analysis_registry.py
RAI/Analysis/AdversarialAnalysis/__init__.py
RAI/Analysis/AdversarialAnalysis/adversarial_tree_analysis.py
RAI/Analysis/AdversarialAnalysis/clever_targeted_score.py
RAI/Analysis/AdversarialAnalysis/clever_untargeted_score.py
RAI/Analysis/AdversarialAnalysis/generate_bb_adversarial_image.py
RAI/Analysis/FairnessAnalysis/__init__.py
RAI/Analysis/FairnessAnalysis/fairness_analysis.py
RAI/Analysis/VisualizationAnalysis/__init__.py
RAI/Analysis/VisualizationAnalysis/data_visualization.py
RAI/Analysis/VisualizationAnalysis/gradcam_analysis.py
RAI/Analysis/VisualizationAnalysis/view_inference_analysis.py
RAI/certificates/__init__.py
RAI/certificates/certificate.py
RAI/certificates/certificate_manager.py
RAI/certificates/standard/adversarial_bound_bronze_certs.json
RAI/certificates/standard/adversarial_bound_gold_certs.json
RAI/certificates/standard/adversarial_bound_silver_certs.json
RAI/certificates/standard/adversarial_error_bronze_certs.json
RAI/certificates/standard/adversarial_error_gold_certs.json
RAI/certificates/standard/adversarial_error_silver_certs.json
RAI/certificates/standard/adversarial_gold_standard.json
RAI/certificates/standard/cert_list.json
RAI/certificates/standard/clever_l1_certs_bronze.json
RAI/certificates/standard/clever_l1_certs_gold.json
RAI/certificates/standard/clever_l1_certs_silver.json
RAI/certificates/standard/clever_l2_certs_bronze.json
RAI/certificates/standard/clever_l2_certs_gold.json
RAI/certificates/standard/clever_l2_certs_silver.json
RAI/certificates/standard/clever_li_certs_bronze.json
RAI/certificates/standard/clever_li_certs_gold.json
RAI/certificates/standard/clever_li_certs_silver.json
RAI/certificates/standard/empty_cert_list.json
