Metadata-Version: 2.1
Name: OpenRAI
Version: 1.0.0
Summary: Responsible AI framework.
Home-page: UNKNOWN
Author: Ali Payani
Author-email: apayani@cisco.com
License: UNKNOWN
Platform: UNKNOWN
Provides-Extra: dashboard
License-File: LICENSE
